archinfo/__init__.py
archinfo/arch.py
archinfo/arch_aarch64.py
archinfo/arch_amd64.py
archinfo/arch_arm.py
archinfo/arch_mips32.py
archinfo/arch_mips64.py
archinfo/arch_pcode.py
archinfo/arch_ppc32.py
archinfo/arch_ppc64.py
archinfo/arch_riscv64.py
archinfo/arch_s390x.py
archinfo/arch_soot.py
archinfo/arch_x86.py
archinfo/archerror.py
archinfo/py.typed
archinfo/tls.py
archinfo/types.py
archinfo-9.2.193.dist-info/licenses/LICENSE
archinfo-9.2.193.dist-info/METADATA
archinfo-9.2.193.dist-info/WHEEL
archinfo-9.2.193.dist-info/top_level.txt
archinfo-9.2.193.dist-info/RECORD
